jnb2py/__init__.py
jnb2py/nbconverter.py
jnb2py/utils.py
jnb2py/models/__init__.py
jnb2py/models/cell_model.py
jnb2py/models/notebook_model.py
tests/__init__.py
tests/test_nbconverter.py
jnb2py-0.0.2.dist-info/LICENSE
jnb2py-0.0.2.dist-info/METADATA
jnb2py-0.0.2.dist-info/WHEEL
jnb2py-0.0.2.dist-info/top_level.txt
jnb2py-0.0.2.dist-info/RECORD
