Metadata-Version: 2.1
Name: jnb2py
Version: 0.0.2
Summary: Converts .ipynb files to .py files.
Home-page: https://github.com/subhranil2605/nb2py
Author: Subhranil Sarkar
Author-email: subhranil2605@gmail.com
License: MIT
Classifier: Programming Language :: Python :: 3.10
Classifier: Operating System :: OS Independent
Requires-Python: >=3.10
License-File: LICENSE
Provides-Extra: dev
Requires-Dist: pytest (>=7.0) ; extra == 'dev'
Requires-Dist: twine (>=4.0.2) ; extra == 'dev'
